LICENSE
MANIFEST.in
README.md
setup.cfg
setup.py
versioneer.py
docs/pydocmd.yml
examples/3d/audio.ogg
examples/3d/bass_example.py
examples/3dpackfile/bass_example.py
examples/3dpackfile/sound/sound.pak
examples/demo1/info.txt
examples/demo1/input_demo.py
examples/demo1/main.py
examples/demo1/main2.py
lucia/__init__.py
lucia/_version.py
lucia/data.py
lucia/output.py
lucia/packfile.py
lucia.egg-info/PKG-INFO
lucia.egg-info/SOURCES.txt
lucia.egg-info/dependency_links.txt
lucia.egg-info/entry_points.txt
lucia.egg-info/not-zip-safe
lucia.egg-info/requires.txt
lucia.egg-info/top_level.txt
lucia/audio/__init__.py
lucia/audio/backend.py
lucia/audio/sound.py
lucia/audio/soundpool.py
lucia/audio/bass/__init__.py
lucia/audio/bass/sound.py
lucia/audio/bass/sound_positioning.py
lucia/audio/bass/soundpool.py
lucia/audio/fmod/__init__.py
lucia/audio/openal/__init__.py
lucia/audio/openal/loaders.py
lucia/audio/openal/sound.py
lucia/audio/openal/soundpool.py
lucia/cli/__init__.py
lucia/cli/packer.py
lucia/lib/32bit/OpenAL32.dll
lucia/lib/64bit/OpenAL32.dll
lucia/ui/__init__.py
lucia/ui/menu.py
lucia/ui/menu2.py
lucia/ui/virtualinput.py
lucia/utils/__init__.py
lucia/utils/instance_checker.py
lucia/utils/network.py
lucia/utils/number_to_words.py
lucia/utils/rotation.py
lucia/utils/timer.py
tests/__init__.py
tests/audio.ogg
tests/test.dat
tests/test_audiobackends.py
tests/test_data.py
tests/test_initialization.py
tests/test_packfile.py
tests/util.py